TaxoSS/__init__.py
TaxoSS/calculate_IC.py
TaxoSS/create_card_cache.py
TaxoSS/functions.py
TaxoSS/data/card_cache.csv
TaxoSS/data/card_cache_star.csv
TaxoSS/data/information_content_default.csv
TaxoSS-0.1.5.dist-info/METADATA
TaxoSS-0.1.5.dist-info/WHEEL
TaxoSS-0.1.5.dist-info/top_level.txt
TaxoSS-0.1.5.dist-info/RECORD
