Metadata-Version: 2.1
Name: TaxoSS
Version: 0.1.5
Summary: Semantic similarity computation with different state-of-the-art metrics
Home-page: UNKNOWN
Author: Lorenzo Malandri
Author-email: lorenzo.malandri@unimib.it
License: UNKNOWN
Platform: UNKNOWN
Classifier: Intended Audience :: Developers
Classifier: Programming Language :: Python :: 3.6
Classifier: Programming Language :: Python :: 3.7
Classifier: Programming Language :: Python :: 3.8
Classifier: Programming Language :: Python :: 3.9
Classifier: Operating System :: OS Independent
Requires-Dist: nltk
Requires-Dist: numpy
Requires-Dist: pandas
